truthai_sdk/__init__.py
truthai_sdk-0.0.2.dist-info/licenses/LICENSE
truthai_sdk-0.0.2.dist-info/METADATA
truthai_sdk-0.0.2.dist-info/WHEEL
truthai_sdk-0.0.2.dist-info/top_level.txt
truthai_sdk-0.0.2.dist-info/RECORD
